contact_form_bootstrap/__init__.py
contact_form_bootstrap/forms.py
contact_form_bootstrap/models.py
contact_form_bootstrap/settings.py
contact_form_bootstrap/urls.py
contact_form_bootstrap/views.py
contact_form_bootstrap/templates/contact.html
contact_form_bootstrap/templates/contact_completed.html
contact_form_bootstrap/templates/email_message.txt
contact_form_bootstrap/templates/email_subject.txt
django_contactform_bootstrap-0.5.10.dist-info/DESCRIPTION.rst
django_contactform_bootstrap-0.5.10.dist-info/METADATA
django_contactform_bootstrap-0.5.10.dist-info/metadata.json
django_contactform_bootstrap-0.5.10.dist-info/pbr.json
django_contactform_bootstrap-0.5.10.dist-info/RECORD
django_contactform_bootstrap-0.5.10.dist-info/top_level.txt
django_contactform_bootstrap-0.5.10.dist-info/WHEEL
example/__init__.py
example/manage.py
example/settings.py
example/settings_tests.py
example/urls.py
example/views.py
example/wsgi.py
