Metadata-Version: 2.0
Name: django-contactform-bootstrap
Version: 0.5.10
Summary: A Django Base contact form with bootstrap 3 and map.
Home-page: http://www.github.com/alainivars/contact_form_bootstrap/
Author: James Bennett, Alain Ivars
Author-email: alainivars@highfeature.com
License: BSD License
Platform: UNKNOWN
Classifier: Development Status :: 5 - Production/Stable
Classifier: Environment :: Web Environment
Classifier: Framework :: Django
Classifier: Intended Audience :: Developers
Classifier: License :: OSI Approved :: BSD License
Classifier: Operating System :: OS Independent
Classifier: Programming Language :: Python
Classifier: Programming Language :: Python :: 3
Classifier: Programming Language :: Python :: 2.7
Classifier: Programming Language :: Python :: 3.4
Classifier: Topic :: Internet :: WWW/HTTP
Classifier: Topic :: Internet :: WWW/HTTP :: Dynamic Content
Requires-Dist: django-crispy-bootstrap (>=0.1.1.1)
Requires-Dist: django-crispy-forms-ng (==2.0.0)
Requires-Dist: requests (>=2.7.0)
Provides-Extra: tests
Requires-Dist: pytest; extra == 'tests'
Requires-Dist: pytest-cov (>=1.4); extra == 'tests'
Requires-Dist: pytest-django; extra == 'tests'
Requires-Dist: mock; extra == 'tests'
Requires-Dist: cov-core (>=1.15.0); extra == 'tests'
Requires-Dist: coverage (>=3.7.1); extra == 'tests'
Provides-Extra: prod
Provides-Extra: dev
Requires-Dist: django-extensions (==1.5.5); extra == 'dev'
Requires-Dist: django-debug-toolbar (==1.3.0); extra == 'dev'
